ryanair/__init__.py
ryanair/airport_utils.py
ryanair/airports.csv
ryanair/ryanair.py
ryanair/types.py
ryanair_py-2.3.1.dist-info/LICENSE.md
ryanair_py-2.3.1.dist-info/METADATA
ryanair_py-2.3.1.dist-info/WHEEL
ryanair_py-2.3.1.dist-info/top_level.txt
ryanair_py-2.3.1.dist-info/RECORD
