Metadata-Version: 2.1
Name: ryanair-py
Version: 2.3.1
Summary: A module which allows you to retrieve data about the cheapest one-way and return flights in a date range, or all available flights on a given day for a given route.
Home-page: https://github.com/cohaolain/ryanair-py
Author: Ciarán Ó hAoláin
Author-email: ciaran@cohaolain.ie
Classifier: Programming Language :: Python :: 3
Classifier: Operating System :: OS Independent
License-File: LICENSE.md
